pirant
