Metadata-Version: 1.1
Name: pirant
Version: 0.1.4.dev1
Summary: DevRant wrapper in Python
Home-page: https://github.com/aayush26/pirant
Author: aayush
Author-email: aayushsingh.mail@gmail.com
License: MIT
Keywords: devrant api wrapper
Platform: UNKNOWN
Classifier: Programming Language :: Python :: 2.7
